pyuutils-0.0.1.dist-info/RECORD
pyuutils-0.0.1.dist-info/METADATA
pyuutils-0.0.1.dist-info/WHEEL
pyuutils-0.0.1.dist-info/top_level.txt
pyuutils-0.0.1.dist-info/LICENSE
pyuutils/__init__.py
pyuutils/base/platform.py
pyuutils/base/time.py
pyuutils/base/random.py
pyuutils/base/__init__.py
pyuutils/base/relation.py
pyuutils/hash/compute.py
pyuutils/hash/__init__.py
pyuutils/_core/_c_uutils_base_platform.cpython-38-s390x-linux-gnu.so
pyuutils/_core/_c_uutils_base_time.cpython-38-s390x-linux-gnu.so
pyuutils/_core/_c_uutils_base_random.cpython-38-s390x-linux-gnu.so
pyuutils/_core/__init__.py
pyuutils/_core/_c_uutils_base_relation.cpython-38-s390x-linux-gnu.so
pyuutils/_core/_c_uutils_hash_compute.cpython-38-s390x-linux-gnu.so
pyuutils/config/__init__.py
pyuutils/config/meta.py
